community_detection/FN.py
community_detection/GN.py
community_detection/LPA.py
community_detection/__init__.py
community_detection/community_utility.py
community_detection/cpm.py
community_detection/em.py
community_detection/fast_unfolding.py
tests/__init__.py
tests/test_cpm.py
tests/test_em.py
tests/test_fast_unfolding.py
tests/test_fn.py
tests/test_gn.py
tests/test_lpa.py
community_detection-0.0.14.dist-info/METADATA
community_detection-0.0.14.dist-info/WHEEL
community_detection-0.0.14.dist-info/top_level.txt
community_detection-0.0.14.dist-info/RECORD
