Metadata-Version: 2.1
Name: community-detection
Version: 0.0.14
Summary: A community detection package
Home-page: https://github.com/jiayingwang/community_detection
Author: Jiaying Wang
Author-email: jiaying@sjzu.edu.cn
License: UNKNOWN
Platform: UNKNOWN
Classifier: Programming Language :: Python :: 3
Classifier: License :: OSI Approved :: MIT License
Classifier: Operating System :: OS Independent
Requires-Python: >=3.6
Requires-Dist: elegant-io
Requires-Dist: simple-graph
